{"k": "acceptPatch", "v": "Accept-Patch", "type": ["res"], "modifyForbidden": true, "corsSafeReq": null, "corsSafeRes": null, "syntax": ["Accept-Patch: application/example, text/example", "Accept-Patch: text/example;charset=utf-8", "Accept-Patch: application/merge-patch+json"], "directives": [], "examples": ["Accept-Patch: application/example, text/example\n\nAccept-Patch: text/example;charset=utf-8\n\nAccept-Patch: application/merge-patch+json\n"], "specs": ["https://tools.ietf.org/html/rfc5789#section-2.2"]}